Workbook

Sheet Assumptions
A1: TechNexus — Pricing Model Assumptions
A3: Parameter | B3: Value | C3: Notes
A4: Air freight rate (USD/kg) | B4: 8 | C4: Dubai -> LLW standard air cargo (TJ)
A5: Markup (multiplier) | B5: 1.35 | C5: 35% margin on landed cost
A6: FX rate (MWK per USD) | B6: 1734 | C6: Per current catalogue.html (Mar 2026)
A7: VAT rate | B7: 0.175 | C7: 17.5% — for buyer info; not pre-loaded

Sheet Catalogue
A1: SKU | B1: Category | C1: Sub-category | D1: Product name | E1: Brand | F1: Supplier (Dubai) | G1: Cost USD | H1: Cost source | I1: Weight kg | J1: Freight USD | K1: Landed USD | L1: Final USD | M1: Final MWK | N1: Include on site?
A2: MT-CCR2116-12G-4S+ | B2: Networking | C2: ISP Core Router | D2: Mikrotik CCR2116-12G-4S+ Cloud Core Router (16GB RAM, 13xGbE, 4xSFP+) | E2: Mikrotik | F2: Roshin Dubai Computer | G2: 1295 | H2: estimated | I2: 3.5 | J2: =I2*Assumptions!$B$4 -> 28 | K2: =G2+J2 -> 1323 | L2: =ROUNDUP((G2+J2)*Assumptions!$B$5,-1) -> 1790 | M2: =L2*Assumptions!$B$6 -> 3103860 | N2: Yes
A3: MT-CCR2216-1G-12XS-2XQ | B3: Networking | C3: ISP Core Router | D3: Mikrotik CCR2216-1G-12XS-2XQ Cloud Core Router (12xSFP28, 2xQSFP28) | E3: Mikrotik | F3: Roshin Dubai Computer | G3: 2995 | H3: estimated | I3: 4 | J3: =I3*Assumptions!$B$4 -> 32 | K3: =G3+J3 -> 3027 | L3: =ROUNDUP((G3+J3)*Assumptions!$B$5,-1) -> 4090 | M3: =L3*Assumptions!$B$6 -> 7092060 | N3: Yes
A4: MT-CCR2004-16G-2S+ | B4: Networking | C4: ISP Edge Router | D4: Mikrotik CCR2004-16G-2S+ Cloud Core Router (16xGbE, 2xSFP+) | E4: Mikrotik | F4: Roshin Dubai Computer | G4: 475 | H4: estimated | I4: 1.5 | J4: =I4*Assumptions!$B$4 -> 12 | K4: =G4+J4 -> 487 | L4: =ROUNDUP((G4+J4)*Assumptions!$B$5,-1) -> 660 | M4: =L4*Assumptions!$B$6 -> 1144440 | N4: Yes
A5: MT-CCR2004-1G-12S+2XS | B5: Networking | C5: ISP Aggregation Router | D5: Mikrotik CCR2004-1G-12S+2XS Cloud Core Router (12xSFP+, 2xSFP28) L6 | E5: Mikrotik | F5: Roshin Dubai Computer | G5: 525 | H5: estimated | I5: 1.5 | J5: =I5*Assumptions!$B$4 -> 12 | K5: =G5+J5 -> 537 | L5: =ROUNDUP((G5+J5)*Assumptions!$B$5,-1) -> 730 | M5: =L5*Assumptions!$B$6 -> 1265820 | N5: Yes
A6: MT-RB5009UPR+S+IN | B6: Networking | C6: Enterprise Router | D6: Mikrotik RB5009UPR+S+IN 7xGbE + 2.5G + SFP+ PoE-in Router | E6: Mikrotik | F6: Roshin Dubai Computer | G6: 295 | H6: estimated | I6: 0.9 | J6: =I6*Assumptions!$B$4 -> 7.2 | K6: =G6+J6 -> 302.2 | L6: =ROUNDUP((G6+J6)*Assumptions!$B$5,-1) -> 410 | M6: =L6*Assumptions!$B$6 -> 710940 | N6: Yes
A7: MT-RB5009UG+S+IN | B7: Networking | C7: Enterprise Router | D7: Mikrotik RB5009UG+S+IN 7xGbE + 2.5G + SFP+ Router | E7: Mikrotik | F7: Roshin Dubai Computer | G7: 240 | H7: estimated | I7: 0.7 | J7: =I7*Assumptions!$B$4 -> 5.6 | K7: =G7+J7 -> 245.6 | L7: =ROUNDUP((G7+J7)*Assumptions!$B$5,-1) -> 340 | M7: =L7*Assumptions!$B$6 -> 589560 | N7: Yes
A8: MT-RB4011iGS+RM | B8: Networking | C8: Enterprise Router | D8: Mikrotik RB4011iGS+RM Rackmount Router (10xGbE, 1xSFP+) | E8: Mikrotik | F8: Roshin Dubai Computer | G8: 199 | H8: estimated | I8: 1.1 | J8: =I8*Assumptions!$B$4 -> 8.8 | K8: =G8+J8 -> 207.8 | L8: =ROUNDUP((G8+J8)*Assumptions!$B$5,-1) -> 290 | M8: =L8*Assumptions!$B$6 -> 502860 | N8: Yes
A9: MT-RB1100DX4 | B9: Networking | C9: Enterprise Router | D9: Mikrotik RB1100AHx4 Dude Edition (RB1100DX4) 13xGbE Router | E9: Mikrotik | F9: Roshin Dubai Computer | G9: 295 | H9: estimated | I9: 1.5 | J9: =I9*Assumptions!$B$4 -> 12 | K9: =G9+J9 -> 307 | L9: =ROUNDUP((G9+J9)*Assumptions!$B$5,-1) -> 420 | M9: =L9*Assumptions!$B$6 -> 728280 | N9: Yes
A10: MT-L009UIGS-RM | B10: Networking | C10: Branch Router | D10: Mikrotik L009UiGS-RM 8xGbE + 2.5G + SFP Router (rackmount) | E10: Mikrotik | F10: Roshin Dubai Computer | G10: 175 | H10: estimated | I10: 0.9 | J10: =I10*Assumptions!$B$4 -> 7.2 | K10: =G10+J10 -> 182.2 | L10: =ROUNDUP((G10+J10)*Assumptions!$B$5,-1) -> 250 | M10: =L10*Assumptions!$B$6 -> 433500 | N10: Yes
A11: MT-CRS354-48G-4S+2Q+RM | B11: Networking | C11: Managed Switch | D11: Mikrotik CRS354-48G-4S+2Q+RM 48xGbE + 4xSFP+ + 2xQSFP+ Switch | E11: Mikrotik | F11: Roshin Dubai Computer | G11: 595 | H11: estimated | I11: 4.5 | J11: =I11*Assumptions!$B$4 -> 36 | K11: =G11+J11 -> 631 | L11: =ROUNDUP((G11+J11)*Assumptions!$B$5,-1) -> 860 | M11: =L11*Assumptions!$B$6 -> 1491240 | N11: Yes
A12: MT-CRS354-48P-4S+2Q+RM | B12: Networking | C12: PoE Managed Switch | D12: Mikrotik CRS354-48P-4S+2Q+RM 48-port PoE Switch + 4xSFP+/2xQSFP+ | E12: Mikrotik | F12: Roshin Dubai Computer | G12: 895 | H12: estimated | I12: 5.5 | J12: =I12*Assumptions!$B$4 -> 44 | K12: =G12+J12 -> 939 | L12: =ROUNDUP((G12+J12)*Assumptions!$B$5,-1) -> 1270 | M12: =L12*Assumptions!$B$6 -> 2202180 | N12: Yes
A13: MT-CRS328-24P-4S+RM | B13: Networking | C13: PoE Switch | D13: Mikrotik CRS328-24P-4S+RM 24-port Gigabit PoE + 4xSFP+ Switch | E13: Mikrotik | F13: Roshin Dubai Computer | G13: 495 | H13: estimated | I13: 4 | J13: =I13*Assumptions!$B$4 -> 32 | K13: =G13+J13 -> 527 | L13: =ROUNDUP((G13+J13)*Assumptions!$B$5,-1) -> 720 | M13: =L13*Assumptions!$B$6 -> 1248480 | N13: Yes
... A36: DEL-MINI-U5 | B36: Desktops | C36: Mini PC | D36: Dell OptiPlex Mini Pro QCM1250 Ultra 5 235T 8GB/512GB BT/WiFi DOS | E36: Dell | F36: Roshin Dubai Computer | G36: 625 | H36: estimated | I36: 2.5 | J36: =I36*Assumptions!$B$4 -> 20 | K36: =G36+J36 -> 645 | L36: =ROUNDUP((G36+J36)*Assumptions!$B$5,-1) -> 880 | M36: =L36*Assumptions!$B$6 -> 1525920 | N36: Yes
K38: Totals | L38: =SUM(L2:L36) -> 29500 | M38: =SUM(M2:M36) -> 51153000

Sheet Removed
A1: Items intentionally NOT on the curated list (and why)
A2: SKU / Item | B2: Reason excluded | C2: Notes
A3: HP Victus 15-FA2082WM / 15-FA2021NIA | B3: Consumer gaming — off-brand for B2B catalogue | C3: Move to personal-buyer channel only
A4: HP Omen 16-AM0073 | B4: Consumer gaming laptop | C4: Not aligned with ISP/enterprise positioning
A5: HP OmniBook 5 Flip 14-FP0023 | B5: Consumer 2-in-1 | C5: Not business-grade
A6: Lenovo YOGA 7i 2-in-1 | B6: Consumer creator laptop | C6: Not business-grade
A7: HP 15-FC0146DX / FD0215DX / FC0057 | B7: Consumer home laptops (AMD Ryzen R5/R7, touch) | C7: Sell only via direct enquiry
A8: Lenovo V15 / V14 G4 budget | B8: Entry-consumer; thin margins | C8: Keep as optional enquiry, not featured
A9: Mikrotik hAP ax lite / ax2 / ax3 (C52/C53/L41) | B9: SMB/home category — excluded by TJ's brief | C9: Roshin qty list heavy but out-of-scope
A10: Mikrotik hEX family (RB750Gr3, RB760iGS, E50UG, E60iUGS) | B10: SMB home router | C10: Ditto
A11: Mikrotik RB941 hAP lite / RB951 / RB952 hAP AC lite | B11: SOHO AP routers | C11: Ditto
A12: Mikrotik LHG / LHGG / QRT / mANTBox (RB911, RBSXTG, RBLHG) | B12: Wireless outdoor CPE — not in chosen scope | C12: Can be added if scope expands
A13: Mikrotik WAP ax / CAP ax / CAP AC (WAPG, CAPGI, RBCAPGI) | B13: Indoor wireless APs — not selected scope | C13: Ditto
... A15: Mikrotik RB911G-2HPND-12S mANTBox 2 | B15: Wireless 2.4 GHz base station — scope out | C15: Ditto

Sheet Site_Replacements
A1: Recommended live-site changes (catalogue.html)
A2: Action | B2: Current on site | C2: Replace with (from Curated) | D2: Reason
A3: REPLACE | B3: HP ProBook 450 G10 — HP-PB450-G10 | C3: HP ProBook 440 G11 — HP-PB440-G11 | D3: Newer gen Ultra 5 platform
A4: REPLACE | B4: Lenovo ThinkPad E15 Gen 4 — LEN-TPE15-G4 | C4: Lenovo ThinkPad E14 Core 5 — LEN-TP-E14-C5 | D4: E-series refresh; 14" is current SKU
A5: REPLACE | B5: Dell Latitude 5540 — DELL-LAT5540 | C5: Dell OptiPlex QCT1250 i5 — DEL-QCT1250-I5 (or keep Latitude only on enquiry) | D5: Supplier stock is on desktop line; Latitude not in ready stock
A6: REPLACE | B6: HP EliteDesk 800 G9 Tower — HP-ED800-G9 | C6: HP EliteDesk 800 G9 SFF i7 — HP-800-G9-SFF-I7 | D6: Current ready stock is SFF i7 spec
A7: REPLACE | B7: Dell OptiPlex 7010 Tower — DELL-OPT7010 | C7: Dell OptiPlex 7020 i3 — DEL-7020-I3 | D7: Newer 14th-gen on ready stock list
A8: REPLACE | B8: Lenovo ThinkCentre M70t Gen 4 — LEN-M70T-G4 | C8: Lenovo ThinkCentre M70t TWR i7 — LEN-TC-M70T-I7 (or M70s SFF i5 LEN-TC-M70S-I5) | D8: Current ready stock Gen5/14-gen
A9: ADD | B9: — | C9: All curated Mikrotik ISP lines (CCR2116, CCR2216, CCR2004, CRS354, CRS328, CRS326, CRS318, CRS112, RB5009UG+, RB5009UPR+, RB4011, RB1100DX4, L009UiGS) | D9: ISP vertical missing from current site; huge opportunity
A10: ADD | B10: — | C10: Mikrotik S+85DLC03D 10G-SR SFP+ + S+RJ10 copper SFP+ | D10: Accessory attach-sales on every switch quote
A11: REVIEW | B11: HPE Aruba 1930 24G Switch (HPE-ARU1930-24G) | C11: Mikrotik CRS326-24G-2S+RM or CRS328-24P-4S+RM | D11: Both cheaper & available from Dubai supplier
A12: REVIEW | B12: Synology RT6600ax Router (SYN-RT6600AX) | C12: Mikrotik RB5009UG+S+IN (+ cAP/hAP for WiFi) or keep both | D12: Mikrotik already in supplier line

Sheet Icon_Search_Terms
A1: Image / icon search terms — per curated SKU
A2: File convention: lowercase-hyphenated, max 40 chars, -1200w.jpg + -800w.webp + -400w.webp variants. Prefer vendor/press-kit imagery (mikrotik.com/products, lenovo.com/support/images, hp.com/support, dell.com).
A3: SKU | B3: Filename (base) | C3: Target folder | D3: Primary search terms | E3: Fallback search terms
A4: MT-CCR2116-12G-4S+ | B4: mikrotik-ccr2116-12g-4sfp | C4: images/networking/routers/ | D4: mikrotik ccr2116-12g-4s+ product press image | E4: ccr2116 12g 4sfp+ official mikrotik.com
A5: MT-CCR2216-1G-12XS-2XQ | B5: mikrotik-ccr2216-1g-12xs-2xq | C5: images/networking/routers/ | D5: mikrotik ccr2216 1g 12xs 2xq 100g router | E5: ccr2216 official product photo mikrotik
A6: MT-CCR2004-16G-2S+ | B6: mikrotik-ccr2004-16g-2sfp | C6: images/networking/routers/ | D6: mikrotik ccr2004 16g 2s+ png | E6: ccr2004-16g-2sfp cloud core router image
A7: MT-CCR2004-1G-12S+2XS | B7: mikrotik-ccr2004-12sfp-2xs | C7: images/networking/routers/ | D7: mikrotik ccr2004 1g 12s+ 2xs 25g | E7: ccr2004 12sfp+ aggregation router
A8: MT-RB5009UPR+S+IN | B8: mikrotik-rb5009upr-s-in | C8: images/networking/routers/ | D8: mikrotik rb5009upr+s+in poe router | E8: rb5009 upr product image
A9: MT-RB5009UG+S+IN | B9: mikrotik-rb5009ug-s-in | C9: images/networking/routers/ | D9: mikrotik rb5009ug+s+in router | E9: rb5009 ug s in press photo
A10: MT-RB4011iGS+RM | B10: mikrotik-rb4011igs-rm | C10: images/networking/routers/ | D10: mikrotik rb4011igs+rm rackmount | E10: rb4011 igs rm 10 gigabit router
A11: MT-RB1100DX4 | B11: mikrotik-rb1100dx4 | C11: images/networking/routers/ | D11: mikrotik rb1100ahx4 dude edition | E11: rb1100dx4 rackmount router
A12: MT-L009UIGS-RM | B12: mikrotik-l009uigs-rm | C12: images/networking/routers/ | D12: mikrotik l009uigs-rm router | E12: l009 uigs rm rackmount
A13: MT-CRS354-48G-4S+2Q+RM | B13: mikrotik-crs354-48g-4sfp-2qsfp | C13: images/networking/switches/ | D13: mikrotik crs354-48g-4s+2q+rm switch | E13: crs354 48 port gigabit 40g uplink
A14: MT-CRS354-48P-4S+2Q+RM | B14: mikrotik-crs354-48p-poe | C14: images/networking/switches/ | D14: mikrotik crs354-48p-4s+2q+rm poe | E14: crs354 48 port poe switch mikrotik
... A38: DEL-MINI-U5 | B38: dell-optiplex-mini-pro-qcm1250 | C38: images/desktops/mini/ | D38: dell optiplex mini pro qcm1250 ultra 5 235t | E38: dell mini pro mff image

Sheet Folder_Plan
A1: Image folder restructure plan (target state)
A2: Folder (new) | B2: Purpose
A3: images/branding/ | B3: Brand logos (HP, Dell, Lenovo, Mikrotik, Synology, APC, Canon) — svg preferred, png fallback
A4: images/hero/ | B4: Page hero images (index, catalogue, services). webp @ 1600/1200/800 variants
A5: images/laptops/ | B5: Business laptops — one jpg/webp per SKU, -400/-800/-1200 variants
A6: images/desktops/tower/ | B6: Business tower PCs
A7: images/desktops/sff/ | B7: Small form-factor desktops
A8: images/desktops/mini/ | B8: Mini-PC / TFF form factor
A9: images/networking/routers/ | B9: Mikrotik CCR / RB routers
A10: images/networking/switches/ | B10: Mikrotik CRS switches
A11: images/networking/transceivers/ | B11: SFP+ / QSFP+ modules
A12: images/peripherals/ | B12: Keyboards, mice, monitors, cables
A13: images/ups/ | B13: APC and other UPS units
... A24: (rename) Products_logos/ -> images/branding/ | B24: Standardize case & location
